<Ui xmlns="http://www.blizzard.com/wow/ui/" xmlns:xsi="http://www.w3.org/2001/XMLSchema-instance" xsi:schemaLocation="http://www.blizzard.com/wow/ui/
..\..\FrameXML\UI_shared.xsd">
	<Script file="Blizzard_SelectorUI.lua"/>

	<Button name="SelectorButtonTemplate" mixin="SelectorButtonMixin" virtual="true">
		<Size x="36" y="36"/>
		<Layers>
			<Layer level="BACKGROUND">
				<Texture file="Interface\Buttons\UI-EmptySlot-Disabled">
					<Size x="45" y="45"/>
					<Anchors>
						<Anchor point="CENTER" x="0" y="-1"/>
					</Anchors>
					<TexCoords left="0.140625" right="0.84375" top="0.140625" bottom="0.84375"/>
				</Texture>
			</Layer>
			<Layer level="OVERLAY">
				<Texture parentKey="SelectedTexture" alphaMode="ADD" file="Interface\Buttons\CheckButtonHilight" hidden="true"/>
			</Layer>
		</Layers>
		<Scripts>
			<OnClick method="OnClick"/>
		</Scripts>
		<NormalTexture parentKey="Icon">
			<Size x="36" y="36"/>
			<Anchors>
				<Anchor point="CENTER" x="0" y="-1"/>
			</Anchors>
		</NormalTexture>
		<HighlightTexture parentKey="Highlight" alphaMode="ADD" file="Interface\Buttons\ButtonHilight-Square"/>
	</Button>

	<Frame name="SelectorTemplate" mixin="SelectorMixin" virtual="true">
		<!--
		templateType: frame type for new buttons (should match buttonTemplate's type).
		buttonTemplate: template to use for new buttons.
		-->
		<KeyValues>
			<KeyValue key="templateType" value="BUTTON" type="string"/>
			<KeyValue key="buttonTemplate" value="SelectorButtonTemplate" type="string"/>
		</KeyValues>
		<Scripts>
			<OnShow method="OnShow"/>
		</Scripts>
	</Frame>
</Ui>
