<Ui xmlns="http://www.blizzard.com/wow/ui/" xmlns:xsi="http://www.w3.org/2001/XMLSchema-instance" xsi:schemaLocation="http://www.blizzard.com/wow/ui/
UI_shared.xsd">
	<Script file="DurabilityFrame.lua"/>
	<Frame name="DurabilityFrame" frameStrata="LOW" hidden="false" parent="UIParent" inherits="EditModeDurabilityFrameSystemTemplate, UIParentRightManagedFrameTemplate" mixin="DurabilityFrameMixin">
		<Size x="60" y="75"/>
		<KeyValues>
			<KeyValue key="layoutIndex" value="9" type="number"/>
		</KeyValues>
		<Layers>
			<Layer level="BACKGROUND">
				<Texture name="DurabilityHead" file="Interface\Durability\UI-Durability-Icons">
					<Size x="18" y="22"/>
					<Anchors>
						<Anchor point="TOPRIGHT"/>
					</Anchors>
					<TexCoords left="0" right="0.140625" top="0" bottom="0.171875"/>
				</Texture>
				<Texture name="DurabilityShoulders" file="Interface\Durability\UI-Durability-Icons">
					<Size x="48" y="22"/>
					<Anchors>
						<Anchor point="TOP" relativeTo="DurabilityHead" relativePoint="BOTTOM" x="0" y="16"/>
					</Anchors>
					<TexCoords left="0.140625" right="0.515625" top="0" bottom="0.171875"/>
				</Texture>
				<Texture name="DurabilityChest" file="Interface\Durability\UI-Durability-Icons">
					<Size x="20" y="22"/>
					<Anchors>
						<Anchor point="TOP" relativeTo="DurabilityShoulders" relativePoint="TOP" x="0" y="-7"/>
					</Anchors>
					<TexCoords left="0.515625" right="0.6640625" top="0" bottom="0.171875"/>
				</Texture>
				<Texture name="DurabilityWrists" file="Interface\Durability\UI-Durability-Icons">
					<Size x="44" y="22"/>
					<Anchors>
						<Anchor point="TOP" relativeTo="DurabilityShoulders" relativePoint="BOTTOM" x="0" y="7"/>
					</Anchors>
					<TexCoords left="0.6640625" right="1.0" top="0" bottom="0.171875"/>
				</Texture>
				<Texture name="DurabilityHands" file="Interface\Durability\UI-Durability-Icons">
					<Size x="42" y="18"/>
					<Anchors>
						<Anchor point="TOP" relativeTo="DurabilityWrists" relativePoint="BOTTOM" x="0" y="15"/>
					</Anchors>
					<TexCoords left="0" right="0.328125" top="0.171875" bottom="0.3046875"/>
				</Texture>
				<Texture name="DurabilityWaist" file="Interface\Durability\UI-Durability-Icons">
					<Size x="16" y="5"/>
					<Anchors>
						<Anchor point="TOP" relativeTo="DurabilityChest" relativePoint="BOTTOM" x="0" y="6"/>
					</Anchors>
					<TexCoords left="0.328125" right="0.46875" top="0.171875" bottom="0.203125"/>
				</Texture>
				<Texture name="DurabilityLegs" file="Interface\Durability\UI-Durability-Icons">
					<Size x="29" y="20"/>
					<Anchors>
						<Anchor point="TOP" relativeTo="DurabilityWaist" relativePoint="BOTTOM" x="0" y="2"/>
					</Anchors>
					<TexCoords left="0.46875" right="0.6875" top="0.171875" bottom="0.3203125"/>
				</Texture>
				<Texture name="DurabilityFeet" file="Interface\Durability\UI-Durability-Icons">
					<Size x="41" y="32"/>
					<Anchors>
						<Anchor point="TOP" relativeTo="DurabilityLegs" relativePoint="BOTTOM" x="0" y="8"/>
					</Anchors>
					<TexCoords left="0.6875" right="1.0" top="0.171875" bottom="0.4140625"/>
				</Texture>
				<Texture name="DurabilityWeapon" file="Interface\Durability\UI-Durability-Icons">
					<Size x="20" y="45"/>
					<Anchors>
						<Anchor point="RIGHT" relativeTo="DurabilityWrists" relativePoint="LEFT" x="0" y="-6"/>
					</Anchors>
					<TexCoords left="0" right="0.140625" top="0.3203125" bottom="0.6640625"/>
				</Texture>
				<Texture name="DurabilityShield" file="Interface\Durability\UI-Durability-Icons">
					<Size x="25" y="31"/>
					<Anchors>
						<Anchor point="LEFT" relativeTo="DurabilityWrists" relativePoint="RIGHT" x="0" y="10"/>
					</Anchors>
					<TexCoords left="0.1875" right="0.375" top="0.3203125" bottom="0.5546875"/>
				</Texture>
				<Texture name="DurabilityOffWeapon" file="Interface\Durability\UI-Durability-Icons" hidden="true">
					<Size x="20" y="45"/>
					<Anchors>
						<Anchor point="LEFT" relativeTo="DurabilityWrists" relativePoint="RIGHT" x="0" y="-6"/>
					</Anchors>
					<TexCoords left="0" right="0.140625" top="0.3203125" bottom="0.6640625"/>
				</Texture>
				<Texture name="DurabilityRanged" file="Interface\Durability\UI-Durability-Icons">
					<Size x="28" y="38"/>
					<Anchors>
						<Anchor point="TOP" relativeTo="DurabilityShield" relativePoint="BOTTOM" x="0" y="5"/>
					</Anchors>
					<TexCoords left="0.1875" right="0.3984375" top="0.5546875" bottom="0.84375"/>
				</Texture>
			</Layer>
		</Layers>
		<Scripts>
			<OnLoad method="OnLoad" inherit="prepend"/>
			<OnEvent method="OnEvent"/>
			<OnEnter method="OnEnter"/>
			<OnLeave method="OnLeave"/>
		</Scripts>
	</Frame>
</Ui>
